aiobernhard/__init__.py
aiobernhard/proto_pb2.py
aiobernhard-0.1.1.dist-info/DESCRIPTION.rst
aiobernhard-0.1.1.dist-info/METADATA
aiobernhard-0.1.1.dist-info/RECORD
aiobernhard-0.1.1.dist-info/WHEEL
aiobernhard-0.1.1.dist-info/metadata.json
aiobernhard-0.1.1.dist-info/top_level.txt
